README.rst
setup.py
hamed_advanced/__init__.py
hamed_advanced/tests.py
hamed_advanced.egg-info/PKG-INFO
hamed_advanced.egg-info/SOURCES.txt
hamed_advanced.egg-info/dependency_links.txt
hamed_advanced.egg-info/entry_points.txt
hamed_advanced.egg-info/not-zip-safe
hamed_advanced.egg-info/top_level.txt