Metadata-Version: 1.1
Name: hamed-advanced
Version: 1.1
Summary: Simple pair of cipher/decipher functions for hamed advanced mode
Home-page: http://github.com/yeleman/hamed-advanced
Author: renaud gaudin
Author-email: rgaudin@gmail.com
License: Public Domain
Keywords: hamed
Platform: any
Classifier: Development Status :: 4 - Beta
Classifier: Intended Audience :: Developers
Classifier: License :: Public Domain
Classifier: License :: CC0 1.0 Universal (CC0 1.0) Public Domain Dedication
Classifier: Programming Language :: Python
Classifier: Programming Language :: Python :: 2.7
Classifier: Programming Language :: Python :: 3.5
